[{"_id":{"matchId":"5ab7b9f56a5bc30009ff6880","playerId":"72457581-78d3-42a8-b01b-ec14ac2740e6"},"created_at":1521990134144,"updated_at":1521990220854,"i9":"2","nickname":"Ionsto","i10":"0","i13":"4","i15":"0","i6":"17","i14":"1","i7":"2","i16":"0","i8":"17","playerId":"72457581-78d3-42a8-b01b-ec14ac2740e6","c3":"0.74","c2":"1","c4":"24","c1":"1","i19":"0","teamId":"72457581-78d3-42a8-b01b-ec14ac2740e6","i3":"4","i4":"3","i5":"team_Ionsto","premade":false,"c5":"7","bestOf":"1","competitionId":"","date":1521990123000,"game":"csgo","gameMode":"5v5","i0":"EU","i1":"de_cache","i12":"23","i18":"16 / 7","i2":"dedb47bf-49aa-46a0-84d3-4cee3f1f6af1","matchId":"a73b8d39-a33d-441e-aace-834694c7754b","matchRound":"1","played":"1","status":"APPLIED","elo":"1632"},{"_id":{"matchId":"5ab791106b3f03000710e192","playerId":"72457581-78d3-42a8-b01b-ec14ac2740e6"},"created_at":1521979671924,"updated_at":1521979671924,"i9":"4","nickname":"Ionsto","i10":"1","i13":"5","i15":"1","i6":"21","i14":"2","i7":"5","i16":"0","i8":"11","playerId":"72457581-78d3-42a8-b01b-ec14ac2740e6","c3":"1","c2":"1.91","c4":"24","c1":"1","i19":"0","teamId":"72457581-78d3-42a8-b01b-ec14ac2740e6","i3":"12","i4":"4","i5":"team_Ionsto","premade":false,"c5":"16","bestOf":"1","competitionId":"","date":1521976061000,"game":"csgo","gameMode":"5v5","i0":"EU","i1":"de_mirage","i12":"21","i18":"16 / 5","i2":"72457581-78d3-42a8-b01b-ec14ac2740e6","matchId":"46cea356-acdf-4699-9051-f954d5986cb7","matchRound":"1","played":"1","status":"APPLIED"},{"_id":{"matchId":"5ab6d786a05a6500066d11ab","playerId":"72457581-78d3-42a8-b01b-ec14ac2740e6"},"created_at":1521932168764,"updated_at":1521932261049,"i9":"0","nickname":"Ionsto","i10":"0","i13":"8","i15":"0","i6":"16","i14":"0","i7":"3","i16":"0","i8":"22","playerId":"72457581-78d3-42a8-b01b-ec14ac2740e6","c3":"0.55","c2":"0.73","c4":"50","c1":"1","i19":"0","teamId":"72457581-78d3-42a8-b01b-ec14ac2740e6","i3":"8","i4":"5","i5":"team_Ionsto","premade":false,"c5":"13","bestOf":"1","competitionId":"","date":1521932162000,"game":"csgo","gameMode":"5v5","i0":"EU","i1":"de_cache","i12":"29","i18":"16 / 13","i2":"68ee18af-0998-4f7c-977b-e8499dc95f34","matchId":"8fb5243c-4114-4357-ad24-9d4cc7d5184a","matchRound":"1","played":"1","status":"APPLIED","elo":"1631"},{"_id":{"matchId":"5ab6bbcb4f78cd00064aa7b4","playerId":"72457581-78d3-42a8-b01b-ec14ac2740e6"},"created_at":1521925069743,"updated_at":1521925162852,"i9":"1","nickname":"Ionsto","i10":"0","i13":"12","i15":"1","i6":"22","i14":"0","i7":"3","i16":"0","i8":"27","playerId":"72457581-78d3-42a8-b01b-ec14ac2740e6","c3":"0.61","c2":"0.81","c4":"55","c1":"1","i19":"2","teamId":"72457581-78d3-42a8-b01b-ec14ac2740e6","i3":"7","i4":"8","i5":"team_Ionsto","premade":false,"c5":"17","bestOf":"1","competitionId":"","date":1521925064000,"game":"csgo","gameMode":"5v5","i0":"EU","i1":"de_mirage","i12":"36","i18":"17 / 19","i2":"f09d52e1-082c-413c-8b13-aa3e12d93679","matchId":"0d892082-be52-4c59-ac31-66bd1aeda14e","matchRound":"1","played":"1","status":"APPLIED","elo":"1649"},{"_id":{"matchId":"5ab6bbd16a5bc30007d89258","playerId":"72457581-78d3-42a8-b01b-ec14ac2740e6"},"created_at":1521925074543,"updated_at":1521925074543,"i9":"8","nickname":"Ionsto","i10":"1","i13":"5","i15":"1","i6":"31","i14":"1","i7":"6","i16":"0","i8":"11","playerId":"72457581-78d3-42a8-b01b-ec14ac2740e6","c3":"1.15","c2":"2.82","c4":"16","c1":"1","i19":"0","teamId":"72457581-78d3-42a8-b01b-ec14ac2740e6","i3":"10","i4":"6","i5":"team_Ionsto","premade":false,"c5":"16","bestOf":"1","competitionId":"","date":1521921470000,"game":"csgo","gameMode":"5v5","i0":"EU","i1":"de_mirage","i12":"27","i18":"11 / 16","i2":"72457581-78d3-42a8-b01b-ec14ac2740e6","matchId":"6dce8ae4-fbe5-43e3-a503-4654013c3f7e","matchRound":"1","played":"1","status":"APPLIED"},{"_id":{"matchId":"5ab6a1974f78cd0007f6bb79","playerId":"72457581-78d3-42a8-b01b-ec14ac2740e6"},"created_at":1521918359461,"updated_at":1521918455794,"i9":"1","nickname":"Ionsto","i10":"0","i13":"5","i15":"0","i6":"16","i14":"1","i7":"3","i16":"0","i8":"21","playerId":"72457581-78d3-42a8-b01b-ec14ac2740e6","c3":"0.59","c2":"0.76","c4":"31","c1":"1","i19":"0","teamId":"72457581-78d3-42a8-b01b-ec14ac2740e6","i3":"8","i4":"3","i5":"team_Ionsto","premade":false,"c5":"11","bestOf":"1","competitionId":"","date":1521918358000,"game":"csgo","gameMode":"5v5","i0":"EU","i1":"de_cache","i12":"27","i18":"11 / 16","i2":"f2580098-3cf6-4eb5-aeb1-bc6a4c2878e1","matchId":"f0ea7528-d577-416e-ba43-35dd6bdda680","matchRound":"1","played":"1","status":"APPLIED","elo":"1644"},{"_id":{"matchId":"5ab694756a5bc30007d887d5","playerId":"72457581-78d3-42a8-b01b-ec14ac2740e6"},"created_at":1521915003937,"updated_at":1521915090193,"i9":"2","nickname":"Ionsto","i10":"0","i13":"7","i15":"0","i6":"12","i14":"1","i7":"1","i16":"0","i8":"17","playerId":"72457581-78d3-42a8-b01b-ec14ac2740e6","c3":"0.5","c2":"0.71","c4":"58","c1":"1","i19":"0","teamId":"72457581-78d3-42a8-b01b-ec14ac2740e6","i3":"6","i4":"2","i5":"team_Ionsto","premade":false,"c5":"8","bestOf":"1","competitionId":"","date":1521914993000,"game":"csgo","gameMode":"5v5","i0":"EU","i1":"de_mirage","i12":"24","i18":"8 / 16","i2":"83b66ce5-cf5d-417a-801a-e13912219fec","matchId":"7287ad00-0bf2-4c54-bf35-52bdbe42b9bb","matchRound":"1","played":"1","status":"APPLIED","elo":"1667"},{"_id":{"matchId":"5ab66ef54f78cd0007ddcdea","playerId":"72457581-78d3-42a8-b01b-ec14ac2740e6"},"created_at":1521905399159,"updated_at":1521905497016,"i9":"4","nickname":"Ionsto","i10":"0","i13":"11","i15":"1","i6":"26","i14":"0","i7":"7","i16":"0","i8":"31","playerId":"72457581-78d3-42a8-b01b-ec14ac2740e6","c3":"0.44","c2":"0.84","c4":"42","c1":"1","i19":"13","teamId":"72457581-78d3-42a8-b01b-ec14ac2740e6","i3":"10","i4":"5","i5":"team_Ionsto","premade":false,"c5":"28","bestOf":"1","competitionId":"","date":1521905395000,"game":"csgo","gameMode":"5v5","i0":"EU","i1":"de_inferno","i12":"59","i18":"28 / 31","i2":"1c9a06ac-e610-4170-a4ff-118698fd7c12","matchId":"8353c450-9047-4787-a02e-510574bc7e2b","matchRound":"1","played":"1","status":"APPLIED","elo":"1688"},{"_id":{"matchId":"5ab6364a4f78cd000797b5ad","playerId":"72457581-78d3-42a8-b01b-ec14ac2740e6"},"created_at":1521890891593,"updated_at":1521890989129,"i9":"5","nickname":"Ionsto","i10":"1","i13":"8","i15":"1","i6":"36","i14":"2","i7":"6","i16":"0","i8":"15","playerId":"72457581-78d3-42a8-b01b-ec14ac2740e6","c3":"1.2","c2":"2.4","c4":"22","c1":"1","i19":"0","teamId":"72457581-78d3-42a8-b01b-ec14ac2740e6","i3":"8","i4":"8","i5":"team_Ionsto","premade":false,"c5":"16","bestOf":"1","competitionId":"","date":1521890889000,"game":"csgo","gameMode":"5v5","i0":"EU","i1":"de_inferno","i12":"30","i18":"16 / 14","i2":"72457581-78d3-42a8-b01b-ec14ac2740e6","matchId":"248960c7-6b7a-478c-837c-4b8c260bac1a","matchRound":"1","played":"1","status":"APPLIED","elo":"1714"},{"_id":{"matchId":"5ab6264da05a650006fdbc78","playerId":"72457581-78d3-42a8-b01b-ec14ac2740e6"},"created_at":1521886798145,"updated_at":1521886901087,"i9":"1","nickname":"Ionsto","i10":"1","i13":"8","i15":"1","i6":"19","i14":"1","i7":"4","i16":"0","i8":"19","playerId":"72457581-78d3-42a8-b01b-ec14ac2740e6","c3":"0.7","c2":"1","c4":"42","c1":"1","i19":"0","teamId":"72457581-78d3-42a8-b01b-ec14ac2740e6","i3":"9","i4":"7","i5":"team_Ionsto","premade":false,"c5":"16","bestOf":"1","competitionId":"","date":1521886797000,"game":"csgo","gameMode":"5v5","i0":"EU","i1":"de_cache","i12":"27","i18":"16 / 11","i2":"72457581-78d3-42a8-b01b-ec14ac2740e6","matchId":"c6bb7c43-fe71-4e74-9273-9ad998214b08","matchRound":"1","played":"1","status":"APPLIED","elo":"1689"},{"_id":{"matchId":"5ab55ffbb4fc8c0007029ea5","playerId":"72457581-78d3-42a8-b01b-ec14ac2740e6"},"created_at":1521836027931,"updated_at":1521836126577,"i9":"3","nickname":"Ionsto","i10":"1","i13":"10","i15":"0","i6":"26","i14":"2","i7":"7","i16":"0","i8":"14","playerId":"72457581-78d3-42a8-b01b-ec14ac2740e6","c3":"1.04","c2":"1.86","c4":"38","c1":"1","i19":"0","teamId":"72457581-78d3-42a8-b01b-ec14ac2740e6","i3":"10","i4":"6","i5":"team_Ionsto","premade":false,"c5":"16","bestOf":"1","competitionId":"","date":1521836025000,"game":"csgo","gameMode":"5v5","i0":"EU","i1":"de_mirage","i12":"25","i18":"9 / 16","i2":"72457581-78d3-42a8-b01b-ec14ac2740e6","matchId":"c9134830-9d70-44f4-9cc0-66ab447f834e","matchRound":"1","played":"1","status":"APPLIED","elo":"1665"},{"_id":{"matchId":"5ab400a6946fe7000656da39","playerId":"72457581-78d3-42a8-b01b-ec14ac2740e6"},"created_at":1521746088627,"updated_at":1521746203625,"i9":"5","nickname":"Ionsto","i10":"1","i13":"13","i15":"0","i6":"24","i14":"2","i7":"7","i16":"0","i8":"13","playerId":"72457581-78d3-42a8-b01b-ec14ac2740e6","c3":"0.96","c2":"1.85","c4":"54","c1":"1","i19":"0","teamId":"72457581-78d3-42a8-b01b-ec14ac2740e6","i3":"10","i4":"6","i5":"team_Ionsto","premade":false,"c5":"16","bestOf":"1","competitionId":"","date":1521746085000,"game":"csgo","gameMode":"5v5","i0":"EU","i1":"de_mirage","i12":"25","i18":"16 / 9","i2":"72457581-78d3-42a8-b01b-ec14ac2740e6","matchId":"1f3d3156-8c76-4d64-bef6-1bb83de71bfd","matchRound":"1","played":"1","status":"APPLIED","elo":"1640"},{"_id":{"matchId":"5ab2e694b4fc8c00074ba1a8","playerId":"72457581-78d3-42a8-b01b-ec14ac2740e6"},"created_at":1521673877278,"updated_at":1521673975084,"i9":"0","nickname":"Ionsto","i10":"0","i13":"4","i15":"0","i6":"4","i14":"0","i7":"2","i16":"0","i8":"17","playerId":"72457581-78d3-42a8-b01b-ec14ac2740e6","c3":"0.24","c2":"0.24","c4":"100","c1":"1","i19":"0","teamId":"8ab37858-0b27-45b5-9afd-1d944a2bd1e8","i3":"1","i4":"0","i5":"team_SantaKing","premade":false,"c5":"1","bestOf":"1","competitionId":"","date":1521673876000,"game":"csgo","gameMode":"5v5","i0":"EU","i1":"de_overpass","i12":"17","i18":"1 / 16","i2":"bfda0dc5-d11f-404f-9b2b-bdcffa552901","matchId":"7023bd3b-3a98-4faf-9436-2daecc39c842","matchRound":"1","played":"1","status":"APPLIED","elo":"1615"},{"_id":{"matchId":"5ab2dea1946fe700064c76f0","playerId":"72457581-78d3-42a8-b01b-ec14ac2740e6"},"created_at":1521675441717,"updated_at":1521675441717,"i9":"4","nickname":"Ionsto","i10":"0","i13":"16","i15":"0","i6":"24","i14":"2","i7":"1","i16":"0","i8":"21","playerId":"72457581-78d3-42a8-b01b-ec14ac2740e6","c3":"0.83","c2":"1.14","c4":"67","c1":"1","i19":"0","teamId":"72457581-78d3-42a8-b01b-ec14ac2740e6","i3":"6","i4":"7","i5":"team_Ionsto","premade":false,"c5":"13","bestOf":"1","competitionId":"","date":1521671839000,"game":"csgo","gameMode":"5v5","i0":"EU","i1":"de_train","i12":"29","i18":"13 / 16","i2":"afa95764-d1e3-45b9-99f8-920779b24666","matchId":"e2230b8b-0b95-416e-b6cb-1ac10df899c5","matchRound":"1","played":"1","status":"APPLIED"},{"_id":{"matchId":"5ab2d487eaa97e0007af50b1","playerId":"72457581-78d3-42a8-b01b-ec14ac2740e6"},"created_at":1521669256272,"updated_at":1521669354041,"i9":"4","nickname":"Ionsto","i10":"1","i13":"13","i15":"0","i6":"18","i14":"1","i7":"8","i16":"0","i8":"20","playerId":"72457581-78d3-42a8-b01b-ec14ac2740e6","c3":"0.64","c2":"0.9","c4":"72","c1":"1","i19":"0","teamId":"72457581-78d3-42a8-b01b-ec14ac2740e6","i3":"9","i4":"7","i5":"team_Ionsto","premade":false,"c5":"16","bestOf":"1","competitionId":"","date":1521669252000,"game":"csgo","gameMode":"5v5","i0":"EU","i1":"de_inferno","i12":"28","i18":"16 / 12","i2":"72457581-78d3-42a8-b01b-ec14ac2740e6","matchId":"9dd4ed61-621e-4635-8d31-beca2144f6d2","matchRound":"1","played":"1","status":"APPLIED","elo":"1669"},{"_id":{"matchId":"5ab2c6a3a05a6500071893c9","playerId":"72457581-78d3-42a8-b01b-ec14ac2740e6"},"created_at":1521665699459,"updated_at":1521665801470,"i9":"4","nickname":"Ionsto","i10":"1","i13":"6","i15":"1","i6":"15","i14":"0","i7":"6","i16":"0","i8":"17","playerId":"72457581-78d3-42a8-b01b-ec14ac2740e6","c3":"0.6","c2":"0.88","c4":"40","c1":"1","i19":"0","teamId":"a5ec421e-cb13-4138-ae64-ed87e4be0172","i3":"10","i4":"6","i5":"team_aloooks","premade":false,"c5":"16","bestOf":"1","competitionId":"","date":1521665698000,"game":"csgo","gameMode":"5v5","i0":"EU","i1":"de_overpass","i12":"25","i18":"9 / 16","i2":"a5ec421e-cb13-4138-ae64-ed87e4be0172","matchId":"7037e0d9-55a3-4777-b742-b3f4bbcca1c5","matchRound":"1","played":"1","status":"APPLIED","elo":"1633"},{"_id":{"matchId":"5ab2c92f4f78cd00072403e8","playerId":"72457581-78d3-42a8-b01b-ec14ac2740e6"},"created_at":1521669952172,"updated_at":1521669952172,"i9":"0","nickname":"Ionsto","i10":"0","i13":"6","i15":"0","i6":"14","i14":"0","i7":"5","i16":"0","i8":"20","playerId":"72457581-78d3-42a8-b01b-ec14ac2740e6","c3":"0.54","c2":"0.7","c4":"43","c1":"1","i19":"0","teamId":"7c6c15b3-04c0-4230-ba5d-ecf590473928","i3":"4","i4":"6","i5":"team_Jcbigtime","premade":false,"c5":"10","bestOf":"1","competitionId":"","date":1521662749000,"game":"csgo","gameMode":"5v5","i0":"EU","i1":"de_overpass","i12":"26","i18":"10 / 16","i2":"a1b33164-8b17-4a65-86cf-8f32e13412ab","matchId":"83a9b9fd-6d14-42fd-ba04-4f2cfe2f3c08","matchRound":"1","played":"1","status":"APPLIED"},{"_id":{"matchId":"5ab19c4feaa97e0006d6dbfe","playerId":"72457581-78d3-42a8-b01b-ec14ac2740e6"},"created_at":1521589327993,"updated_at":1521589422131,"i9":"1","nickname":"Ionsto","i10":"0","i13":"16","i15":"0","i6":"18","i14":"0","i7":"1","i16":"0","i8":"20","playerId":"72457581-78d3-42a8-b01b-ec14ac2740e6","c3":"0.75","c2":"0.9","c4":"89","c1":"1","i19":"0","teamId":"aa5b1943-d80d-4ae5-b47d-a79c0cad389b","i3":"6","i4":"2","i5":"team_MannyRiberaa","premade":false,"c5":"8","bestOf":"1","competitionId":"","date":1521589326000,"game":"csgo","gameMode":"5v5","i0":"EU","i1":"de_cache","i12":"24","i18":"16 / 8","i2":"80f2351f-c787-48ff-bc28-506647d6e5b3","matchId":"a859f15d-b526-4f48-ae16-ca5a098b53ec","matchRound":"1","played":"1","status":"APPLIED","elo":"1633"},{"_id":{"matchId":"5ab192deb4fc8c00073d7e40","playerId":"72457581-78d3-42a8-b01b-ec14ac2740e6"},"created_at":1521586911531,"updated_at":1521586999240,"i9":"1","nickname":"Ionsto","i10":"0","i13":"10","i15":"0","i6":"13","i14":"0","i7":"3","i16":"1","i8":"19","playerId":"72457581-78d3-42a8-b01b-ec14ac2740e6","c3":"0.65","c2":"0.68","c4":"77","c1":"1","i19":"0","teamId":"8f09555e-f687-4564-8cb9-06884aef0e33","i3":"2","i4":"2","i5":"team_MonteLiciouz","premade":false,"c5":"4","bestOf":"1","competitionId":"","date":1521586903000,"game":"csgo","gameMode":"5v5","i0":"EU","i1":"de_mirage","i12":"20","i18":"16 / 4","i2":"b54001e9-c614-4e21-9a6c-37da391a5772","matchId":"3bd39fea-996b-4954-a2c7-6d53328a5e3c","matchRound":"1","played":"1","status":"APPLIED","elo":"1664"},{"_id":{"matchId":"5ab1897e946fe70007c5067f","playerId":"72457581-78d3-42a8-b01b-ec14ac2740e6"},"created_at":1521584511086,"updated_at":1521584606682,"i9":"4","nickname":"Ionsto","i10":"1","i13":"19","i15":"0","i6":"37","i14":"3","i7":"2","i16":"1","i8":"18","playerId":"72457581-78d3-42a8-b01b-ec14ac2740e6","c3":"1.28","c2":"2.06","c4":"51","c1":"1","i19":"0","teamId":"72457581-78d3-42a8-b01b-ec14ac2740e6","i3":"9","i4":"7","i5":"team_Ionsto","premade":false,"c5":"16","bestOf":"1","competitionId":"","date":1521584509000,"game":"csgo","gameMode":"5v5","i0":"EU","i1":"de_inferno","i12":"29","i18":"13 / 16","i2":"72457581-78d3-42a8-b01b-ec14ac2740e6","matchId":"77b6c432-2b7e-4b5c-a268-bf999b2f355c","matchRound":"1","played":"1","status":"APPLIED","elo":"1690"},{"_id":{"matchId":"5ab17c5feaa97e0007ecd72d","playerId":"72457581-78d3-42a8-b01b-ec14ac2740e6"},"created_at":1521581151955,"updated_at":1521581248920,"i9":"3","nickname":"Ionsto","i10":"1","i13":"13","i15":"0","i6":"19","i14":"1","i7":"1","i16":"0","i8":"14","playerId":"72457581-78d3-42a8-b01b-ec14ac2740e6","c3":"0.79","c2":"1.36","c4":"68","c1":"1","i19":"0","teamId":"72457581-78d3-42a8-b01b-ec14ac2740e6","i3":"11","i4":"5","i5":"team_Ionsto","premade":false,"c5":"16","bestOf":"1","competitionId":"","date":1521581148000,"game":"csgo","gameMode":"5v5","i0":"EU","i1":"de_mirage","i12":"24","i18":"16 / 8","i2":"72457581-78d3-42a8-b01b-ec14ac2740e6","matchId":"4af00d0e-4350-456c-9a6a-cedabe6efd46","matchRound":"1","played":"1","status":"APPLIED","elo":"1664"},{"_id":{"matchId":"5ab172afa05a650006c8ed15","playerId":"72457581-78d3-42a8-b01b-ec14ac2740e6"},"created_at":1521578672488,"updated_at":1521578769076,"i9":"0","nickname":"Ionsto","i10":"0","i13":"5","i15":"0","i6":"14","i14":"0","i7":"6","i16":"0","i8":"19","playerId":"72457581-78d3-42a8-b01b-ec14ac2740e6","c3":"0.64","c2":"0.74","c4":"36","c1":"1","i19":"0","teamId":"388e5e0e-0530-4a9e-b4f2-a8004d536226","i3":"4","i4":"2","i5":"bubblebusters","premade":false,"c5":"6","bestOf":"1","competitionId":"","date":1521578666000,"game":"csgo","gameMode":"5v5","i0":"EU","i1":"de_inferno","i12":"22","i18":"16 / 6","i2":"b328ce24-72d1-4d7c-b7e6-5797a3a199ee","matchId":"fcd3b3e3-526a-4617-acff-2736e339e31e","matchRound":"1","played":"1","status":"APPLIED","elo":"1643"},{"_id":{"matchId":"5ab04b9256905f0007dc30ef","playerId":"72457581-78d3-42a8-b01b-ec14ac2740e6"},"created_at":1521503122555,"updated_at":1521503216459,"i9":"1","nickname":"Ionsto","i10":"0","i13":"7","i15":"0","i6":"20","i14":"1","i7":"4","i16":"0","i8":"28","playerId":"72457581-78d3-42a8-b01b-ec14ac2740e6","c3":"0.56","c2":"0.71","c4":"35","c1":"1","i19":"2","teamId":"613da09f-ce5c-459b-bccf-eb3ee4f54ad8","i3":"7","i4":"8","i5":"team_ixonos","premade":false,"c5":"17","bestOf":"1","competitionId":"","date":1521503121000,"game":"csgo","gameMode":"5v5","i0":"EU","i1":"de_mirage","i12":"36","i18":"19 / 17","i2":"2b681f5b-7fbb-4a76-b07f-26a34c64dcc4","matchId":"486f5bea-485e-43c2-9e11-7b548b2664ee","matchRound":"1","played":"1","status":"APPLIED","elo":"1668"},{"_id":{"matchId":"5ab03ccc15d7120006cd1aaf","playerId":"72457581-78d3-42a8-b01b-ec14ac2740e6"},"created_at":1521499344862,"updated_at":1521499448084,"i9":"5","nickname":"Ionsto","i10":"1","i13":"15","i15":"0","i6":"32","i14":"3","i7":"4","i16":"1","i8":"23","playerId":"72457581-78d3-42a8-b01b-ec14ac2740e6","c3":"0.89","c2":"1.39","c4":"47","c1":"1","i19":"4","teamId":"72457581-78d3-42a8-b01b-ec14ac2740e6","i3":"11","i4":"4","i5":"team_Ionsto","premade":false,"c5":"19","bestOf":"1","competitionId":"","date":1521495769000,"game":"csgo","gameMode":"5v5","i0":"EU","i1":"de_cache","i12":"36","i18":"17 / 19","i2":"72457581-78d3-42a8-b01b-ec14ac2740e6","matchId":"d1fb6e46-ce3c-4a27-b700-5315e372b308","matchRound":"1","played":"1","status":"APPLIED","elo":"1687"},{"_id":{"matchId":"5ab020c6855b9c0007e36b27","playerId":"72457581-78d3-42a8-b01b-ec14ac2740e6"},"created_at":1521492167015,"updated_at":1521492264404,"i9":"2","nickname":"Ionsto","i10":"1","i13":"3","i15":"0","i6":"15","i14":"0","i7":"4","i16":"0","i8":"15","playerId":"72457581-78d3-42a8-b01b-ec14ac2740e6","c3":"0.52","c2":"1","c4":"20","c1":"1","i19":"0","teamId":"388e5e0e-0530-4a9e-b4f2-a8004d536226","i3":"5","i4":"11","i5":"bubblebusters","premade":false,"c5":"16","bestOf":"1","competitionId":"","date":1521492166000,"game":"csgo","gameMode":"5v5","i0":"EU","i1":"de_cache","i12":"29","i18":"13 / 16","i2":"388e5e0e-0530-4a9e-b4f2-a8004d536226","matchId":"c035c8e0-b879-4dbe-96c4-3cec4d2242d7","matchRound":"1","played":"1","status":"APPLIED","elo":"1670"},{"_id":{"matchId":"5ab0158629f4aa00064b222e","playerId":"72457581-78d3-42a8-b01b-ec14ac2740e6"},"created_at":1521489289136,"updated_at":1521489385855,"i9":"5","nickname":"Ionsto","i10":"1","i13":"6","i15":"0","i6":"23","i14":"2","i7":"1","i16":"1","i8":"11","playerId":"72457581-78d3-42a8-b01b-ec14ac2740e6","c3":"0.96","c2":"2.09","c4":"26","c1":"1","i19":"0","teamId":"388e5e0e-0530-4a9e-b4f2-a8004d536226","i3":"11","i4":"5","i5":"team_Jcbigtime","premade":false,"c5":"16","bestOf":"1","competitionId":"","date":1521489283000,"game":"csgo","gameMode":"5v5","i0":"EU","i1":"de_inferno","i12":"24","i18":"8 / 16","i2":"388e5e0e-0530-4a9e-b4f2-a8004d536226","matchId":"1f3a956b-cc36-46ef-8640-d9af3dd155dc","matchRound":"1","played":"1","status":"APPLIED","elo":"1644"},{"_id":{"matchId":"5aaec7f429f4aa0007421599","playerId":"72457581-78d3-42a8-b01b-ec14ac2740e6"},"created_at":1521403894848,"updated_at":1521403985432,"i9":"0","nickname":"Ionsto","i10":"0","i13":"6","i15":"0","i6":"11","i14":"0","i7":"7","i16":"0","i8":"25","playerId":"72457581-78d3-42a8-b01b-ec14ac2740e6","c3":"0.42","c2":"0.44","c4":"55","c1":"1","i19":"0","teamId":"c64e834f-54a8-4236-b146-aa8c0106579b","i3":"7","i4":"3","i5":"team_hkk","premade":false,"c5":"10","bestOf":"1","competitionId":"","date":1521403887000,"game":"csgo","gameMode":"5v5","i0":"EU","i1":"de_overpass","i12":"26","i18":"10 / 16","i2":"a088eaea-6dcc-4ef1-aa5a-db715cfdefac","matchId":"2d71ae70-b228-45d7-8006-0c03bb813d5e","matchRound":"1","played":"1","status":"APPLIED","elo":"1620"},{"_id":{"matchId":"5aae74f256905f00067c22ef","playerId":"72457581-78d3-42a8-b01b-ec14ac2740e6"},"created_at":1521382642690,"updated_at":1521382742824,"i9":"2","nickname":"Ionsto","i10":"0","i13":"5","i15":"0","i6":"16","i14":"1","i7":"0","i16":"0","i8":"20","playerId":"72457581-78d3-42a8-b01b-ec14ac2740e6","c3":"0.62","c2":"0.8","c4":"31","c1":"1","i19":"0","teamId":"173dadb9-8cd9-49b5-87ec-a4eb5990a675","i3":"6","i4":"4","i5":"team_Ragemoar","premade":false,"c5":"10","bestOf":"1","competitionId":"","date":1521382641000,"game":"csgo","gameMode":"5v5","i0":"EU","i1":"de_inferno","i12":"26","i18":"10 / 16","i2":"bfda0dc5-d11f-404f-9b2b-bdcffa552901","matchId":"df9f9125-d096-40ce-896f-c67a96f176a4","matchRound":"1","played":"1","status":"APPLIED","elo":"1645"},{"_id":{"matchId":"5aa6fd9f2bcf63000722f19a","playerId":"72457581-78d3-42a8-b01b-ec14ac2740e6"},"created_at":1520893343443,"updated_at":1520893435184,"i9":"3","nickname":"Ionsto","i10":"1","i13":"7","i15":"0","i6":"18","i14":"2","i7":"6","i16":"0","i8":"19","playerId":"72457581-78d3-42a8-b01b-ec14ac2740e6","c3":"0.72","c2":"0.95","c4":"39","c1":"1","i19":"0","teamId":"30554105-2bce-484b-836b-15698a494763","i3":"12","i4":"4","i5":"team_Jcbigtime","premade":false,"c5":"16","bestOf":"1","competitionId":"","date":1520893336000,"game":"csgo","gameMode":"5v5","i0":"EU","i1":"de_cache","i12":"25","i18":"9 / 16","i2":"30554105-2bce-484b-836b-15698a494763","matchId":"bc17ab0f-6b74-4bfd-a05a-e86d6e26b769","matchRound":"1","played":"1","status":"APPLIED","elo":"1667"},{"_id":{"matchId":"5aa6f2b47cf45f00074bbe87","playerId":"72457581-78d3-42a8-b01b-ec14ac2740e6"},"created_at":1520890548856,"updated_at":1520890645375,"i9":"2","nickname":"Ionsto","i10":"0","i13":"11","i15":"1","i6":"23","i14":"1","i7":"1","i16":"0","i8":"15","playerId":"72457581-78d3-42a8-b01b-ec14ac2740e6","c3":"0.82","c2":"1.53","c4":"48","c1":"1","i19":"0","teamId":"30554105-2bce-484b-836b-15698a494763","i3":"3","i4":"9","i5":"team_Jcbigtime","premade":false,"c5":"12","bestOf":"1","competitionId":"","date":1520890544000,"game":"csgo","gameMode":"5v5","i0":"EU","i1":"de_inferno","i12":"28","i18":"16 / 12","i2":"f91d8b6d-4c11-4436-b0b7-7f270448ba4b","matchId":"02e72a65-b785-4dc0-97d0-332ce714bb87","matchRound":"1","played":"1","status":"APPLIED","elo":"1642"}]